README
setup.py
tinybuddhawisdom/__init__.py
tinybuddhawisdom/app.py
tinybuddhawisdom.egg-info/PKG-INFO
tinybuddhawisdom.egg-info/SOURCES.txt
tinybuddhawisdom.egg-info/dependency_links.txt
tinybuddhawisdom.egg-info/entry_points.txt
tinybuddhawisdom.egg-info/top_level.txt